django_structlog/__init__.py
django_structlog/app_settings.py
django_structlog/apps.py
django_structlog/commands.py
django_structlog/py.typed
django_structlog/signals.py
django_structlog/celery/__init__.py
django_structlog/celery/receivers.py
django_structlog/celery/signals.py
django_structlog/celery/steps.py
django_structlog/middlewares/__init__.py
django_structlog/middlewares/request.py
django_structlog-9.1.0.dist-info/licenses/LICENSE.rst
django_structlog-9.1.0.dist-info/METADATA
django_structlog-9.1.0.dist-info/WHEEL
django_structlog-9.1.0.dist-info/top_level.txt
django_structlog-9.1.0.dist-info/RECORD
