Metadata-Version: 2.4
Name: django-structlog
Version: 9.1.0
Summary: Structured Logging for Django
Author-email: Jules Robichaud-Gagnon <j.robichaudg+pypi@gmail.com>
License: MIT
Project-URL: homepage, https://github.com/jrobichaud/django-structlog
Project-URL: repository, https://github.com/jrobichaud/django-structlog
Project-URL: documentation, https://django-structlog.readthedocs.io
Project-URL: tracker, https://github.com/jrobichaud/django-structlog/issues
Project-URL: changelog, https://django-structlog.readthedocs.io/en/latest/changelog.html
Classifier: Development Status :: 5 - Production/Stable
Classifier: Framework :: Django
Classifier: Framework :: Django :: 4.2
Classifier: Framework :: Django :: 5.0
Classifier: Framework :: Django :: 5.1
Classifier: Framework :: Django :: 5.2
Classifier: Programming Language :: Python :: 3
Classifier: Programming Language :: Python :: 3 :: Only
Classifier: Programming Language :: Python :: 3.9
Classifier: Programming Language :: Python :: 3.10
Classifier: Programming Language :: Python :: 3.11
Classifier: Programming Language :: Python :: 3.12
Classifier: Programming Language :: Python :: 3.13
Classifier: Topic :: System :: Logging
Classifier: License :: OSI Approved :: MIT License
Classifier: Operating System :: OS Independent
Classifier: Typing :: Typed
Requires-Python: >=3.9
License-File: LICENSE.rst
Requires-Dist: django>=4.2
Requires-Dist: structlog>=21.4.0
Requires-Dist: asgiref>=3.6.0
Requires-Dist: django-ipware>=6.0.2
Provides-Extra: celery
Requires-Dist: celery>=5.1; extra == "celery"
Provides-Extra: commands
Requires-Dist: django-extensions>=1.4.9; extra == "commands"
Dynamic: license-file
